uims_api/__init__.py
uims_api/exceptions.py
uims_api/session.py
uims_api-0.1.2.dist-info/LICENSE
uims_api-0.1.2.dist-info/METADATA
uims_api-0.1.2.dist-info/WHEEL
uims_api-0.1.2.dist-info/top_level.txt
uims_api-0.1.2.dist-info/RECORD
