Metadata-Version: 2.1
Name: uims-api
Version: 0.1.2
Summary: A Python library to access information via https://uims.cuchd.in
Home-page: https://github.com/cu-unofficial/uims-api
Author: Ritiek Malhotra
Author-email: ritiekmalhotra123@gmail.com
License: MIT
Keywords: uims,chandigarh university,api
Platform: UNKNOWN
Classifier: License :: OSI Approved :: MIT License
Classifier: Programming Language :: Python
Classifier: Programming Language :: Python :: 3
Classifier: Programming Language :: Python :: 3.4
Classifier: Programming Language :: Python :: 3.5
Classifier: Programming Language :: Python :: 3.6
Classifier: Programming Language :: Python :: 3.7
Classifier: Programming Language :: Python :: 3 :: Only
Classifier: Topic :: Utilities
License-File: LICENSE
Requires-Dist: requests (>=2.21.0)
Requires-Dist: beautifulsoup4 (>=4.6.3)
